bnltk/__init__.py
bnltk/bnltk_downloads/__init__.py
bnltk/bnltk_downloads/file_downloader.py
bnltk/pos_tagger/__init__.py
bnltk/pos_tagger/bn_pos_tagger.py
bnltk/pos_tagger/maskingLayer.py
bnltk/pos_tagger/positionalEncoding.py
bnltk/pos_tagger/trained_model.py
bnltk/pos_tagger/transformerEncoderLayer.py
bnltk/stemmer/__init__.py
bnltk/stemmer/stemmer_builder.py
bnltk/tests/__init__.py
bnltk/tests/test_bn_pos_tagger.py
bnltk/tests/test_bn_word_tokenizers.py
bnltk/tests/test_stemmer_builder.py
bnltk/tokenize/__init__.py
bnltk/tokenize/bn_word_tokenizers.py
bnltk-0.7.8.dist-info/LICENSE
bnltk-0.7.8.dist-info/METADATA
bnltk-0.7.8.dist-info/WHEEL
bnltk-0.7.8.dist-info/top_level.txt
bnltk-0.7.8.dist-info/RECORD
