Metadata-Version: 2.1
Name: bnltk
Version: 0.7.8
Summary: BNLTK(Bangla Natural Language Processing Toolkit)
Home-page: https://github.com/ashwoolford/bnltk
Author: Asraf Patoary
Author-email: asrafhossain197@gmail.com
License: UNKNOWN
Platform: UNKNOWN
Classifier: Programming Language :: Python :: 3
Classifier: License :: OSI Approved :: MIT License
Classifier: Operating System :: OS Independent
Requires-Python: >=3.6
License-File: LICENSE
Requires-Dist: black==24.10.0
Requires-Dist: keras==3.6.0
Requires-Dist: numpy==2.0.2
Requires-Dist: requests==2.32.3
Requires-Dist: scikit-learn==1.5.2
Requires-Dist: tensorflow==2.18.0
